LICENSE
MANIFEST.in
README.md
setup.cfg
setup.py
erscipcard/__init__.py
erscipcard/admin.py
erscipcard/apps.py
erscipcard/epfsurls.py
erscipcard/epfsviews.py
erscipcard/evtturls.py
erscipcard/evttviews.py
erscipcard/forms.py
erscipcard/inst.py
erscipcard/models.py
erscipcard/qrurls.py
erscipcard/qrviews.py
erscipcard/tests.py
erscipcard/urls.py
erscipcard/views.py
erscipcard/widget.py
erscipcard/yturls.py
erscipcard/ytviews.py
erscipcard.egg-info/PKG-INFO
erscipcard.egg-info/SOURCES.txt
erscipcard.egg-info/dependency_links.txt
erscipcard.egg-info/requires.txt
erscipcard.egg-info/top_level.txt
erscipcard/static/1.docx
erscipcard/static/2.docx
erscipcard/static/BNAZANIN.TTF
erscipcard/static/BTITR.TTF
erscipcard/static/back.svg
erscipcard/static/custom_modelField_with_formField
erscipcard/static/doc.svg
erscipcard/static/download.png
erscipcard/static/epfs2.zip
erscipcard/static/ersci_app.zip
erscipcard/static/ersci_viddown_tab2-1.4.xpi
erscipcard/static/favicon.ico
erscipcard/static/icon.png
erscipcard/static/inst
erscipcard/static/logo.png
erscipcard/static/main.css
erscipcard/static/manifest.json
erscipcard/static/mic.svg
erscipcard/static/s
erscipcard/static/service-worker.js
erscipcard/static/spinners.css
erscipcard/static/style.css
erscipcard/static/trash.png
erscipcard/static/ytvid.mp4
erscipcard/static/bt/css/bootstrap.min.5.0.css
erscipcard/static/bt/css/bootstrap.min.css
erscipcard/static/bt/css/font-awesome.min.css
erscipcard/static/bt/css/loginstyle.css
erscipcard/static/bt/css/persianDatepicker-default.css
erscipcard/static/bt/css/style.css
erscipcard/static/bt/css/util.css
erscipcard/static/bt/fonts/BNAZANIN.TTF
erscipcard/static/bt/fonts/BTITR.TTF
erscipcard/static/bt/fonts/Vazir.ttf
erscipcard/static/bt/fonts/fontawesome-webfont.ttf
erscipcard/static/bt/js/bootstrap.bundle.min.js
erscipcard/static/bt/js/bootstrap.min.5.1.js
erscipcard/static/bt/js/bootstrap.min.js
erscipcard/static/bt/js/jquery.min.js
erscipcard/static/bt/js/persianDatepicker.js
erscipcard/static/bt/js/popper.min.2.1.js
erscipcard/static/bt/js/scripts.js
erscipcard/static/bt/pics/favicon.ico
erscipcard/static/bt/pics/logo.png
