Metadata-Version: 2.1
Name: erscipcard
Version: 1.78
Summary: Erscipcard is a Django app to create personeli card.
Home-page: https://github.com/epg900/erscipcard.git
Author: epg
Author-email: epg900@gmail.com
License: GNU GENERAL PUBLIC LICENSE
Requires-Python: >=3.7
License-File: LICENSE
Requires-Dist: django
Requires-Dist: docxtpl
Requires-Dist: docx2pdf; platform_system == "Windows"
Requires-Dist: pillow
Requires-Dist: pyqrcode
Requires-Dist: djangorestframework
